abomination.py
abomination-0.2.0.dist-info/METADATA
abomination-0.2.0.dist-info/WHEEL
abomination-0.2.0.dist-info/top_level.txt
abomination-0.2.0.dist-info/RECORD
