Metadata-Version: 2.1
Name: abomination
Version: 0.2.0
Summary: A dumpster fire of metaprogramming and other Python abuses.
Home-page: https://github.com/comabrewer/abomination
Author: Marco Weber
Author-email: marco.weber@hotmail.de
License: MIT
Platform: UNKNOWN
Requires-Python: >=3.7
